scicap/__init__.py
scicap/calendar/__init__.py
scicap/calendar/config.py
scicap/calendar/main.py
scicap/futures/__init__.py
scicap/futures/contract/__init__.py
scicap/futures/contract/config.py
scicap/futures/contract/instrument.py
scicap/futures/contract/product.py
scicap/futures/contract/utils.py
scicap-2021.8.1.dist-info/METADATA
scicap-2021.8.1.dist-info/WHEEL
scicap-2021.8.1.dist-info/top_level.txt
scicap-2021.8.1.dist-info/RECORD
